linref/__init__.py
linref/route.py
linref/events/__init__.py
linref/events/collection.py
linref/events/merge.py
linref/events/spatial.py
linref/events/synthesis.py
linref/events/union.py
linref/experimental/__init__.py
linref/experimental/analysis.py
linref/experimental/curves.py
linref/various/__init__.py
linref/various/geospatial.py
linref-0.1.1.dist-info/LICENSE.rst
linref-0.1.1.dist-info/METADATA
linref-0.1.1.dist-info/WHEEL
linref-0.1.1.dist-info/top_level.txt
linref-0.1.1.dist-info/RECORD
