Metadata-Version: 2.1
Name: linref
Version: 0.1.1
Summary: Linearly referenced data management, manipulation, and operations
Author-email: Tariq Shihadah <tariq.shihadah@gmail.com>
License: MIT License
Project-URL: documentation, https://linref.readthedocs.io/
Project-URL: repository, https://github.com/tariqshihadah/linref
Keywords: python,geospatial,linear,data,event,dissolve,overlay,range,numeric,interval
Classifier: Development Status :: 1 - Planning
Classifier: Intended Audience :: Developers
Classifier: Programming Language :: Python :: 3
Classifier: License :: OSI Approved :: MIT License
Classifier: Operating System :: Unix
Classifier: Operating System :: MacOS :: MacOS X
Classifier: Operating System :: Microsoft :: Windows
Requires-Python: >=3.8
License-File: LICENSE.rst
Requires-Dist: numpy
Requires-Dist: matplotlib
Requires-Dist: shapely >=1.7
Requires-Dist: pandas >=1.1
Requires-Dist: geopandas >=0.10.2
Requires-Dist: rangel >=0.0.7
